gemnify_sdk/__init__.py
gemnify_sdk/contracts/abis/OrderBook.json
gemnify_sdk/contracts/abis/PositionRouter.json
gemnify_sdk/contracts/abis/Reader.json
gemnify_sdk/contracts/abis/RewardRouter.json
gemnify_sdk/contracts/abis/RewardTracker.json
gemnify_sdk/contracts/abis/Router.json
gemnify_sdk/contracts/abis/Token.json
gemnify_sdk/contracts/abis/Vault.json
gemnify_sdk/contracts/addresses/arbitrum-sepolia.json
gemnify_sdk/scripts/__init__.py
gemnify_sdk/scripts/config.py
gemnify_sdk/scripts/gemnify.py
gemnify_sdk/scripts/instance.py
gemnify_sdk/scripts/logging.py
gemnify_sdk/scripts/utils.py
gemnify_sdk/scripts/contracts/__init__.py
gemnify_sdk/scripts/contracts/fee.py
gemnify_sdk/scripts/contracts/liquidity.py
gemnify_sdk/scripts/contracts/order.py
gemnify_sdk/scripts/contracts/position.py
gemnify_sdk/scripts/contracts/reader.py
gemnify_sdk/scripts/contracts/swap.py
gemnify_sdk/scripts/contracts/util.py
gemnify_sdk-0.1.4.dist-info/LICENSE
gemnify_sdk-0.1.4.dist-info/METADATA
gemnify_sdk-0.1.4.dist-info/WHEEL
gemnify_sdk-0.1.4.dist-info/top_level.txt
gemnify_sdk-0.1.4.dist-info/RECORD
