Metadata-Version: 2.1
Name: gemnify_sdk
Version: 0.1.4
Summary: gemnify sdk
Author: fiorea
Classifier: Programming Language :: Python :: 3
Classifier: License :: OSI Approved :: MIT License
Classifier: Operating System :: OS Independent
Requires-Python: >=3.11.9
License-File: LICENSE
Requires-Dist: aiohttp ==3.9.5
Requires-Dist: aiosignal ==1.3.1
Requires-Dist: attrs ==23.2.0
Requires-Dist: bitarray ==2.9.2
Requires-Dist: certifi ==2024.6.2
Requires-Dist: charset-normalizer ==3.3.2
Requires-Dist: ckzg ==1.0.2
Requires-Dist: cytoolz ==0.12.3
Requires-Dist: eth-account ==0.11.2
Requires-Dist: eth-hash ==0.7.0
Requires-Dist: eth-keyfile ==0.8.1
Requires-Dist: eth-keys ==0.5.1
Requires-Dist: eth-rlp ==1.0.1
Requires-Dist: eth-typing ==4.3.1
Requires-Dist: eth-utils ==4.1.1
Requires-Dist: eth-abi ==5.1.0
Requires-Dist: frozenlist ==1.4.1
Requires-Dist: hexbytes ==0.3.1
Requires-Dist: idna ==3.7
Requires-Dist: jsonschema ==4.22.0
Requires-Dist: jsonschema-specifications ==2023.12.1
Requires-Dist: lru-dict ==1.2.0
Requires-Dist: multidict ==6.0.5
Requires-Dist: parsimonious ==0.10.0
Requires-Dist: protobuf ==5.27.1
Requires-Dist: pycryptodome ==3.20.0
Requires-Dist: pyunormalize ==15.1.0
Requires-Dist: referencing ==0.35.1
Requires-Dist: regex ==2024.5.15
Requires-Dist: requests ==2.32.3
Requires-Dist: rlp ==4.0.1
Requires-Dist: rpds-py ==0.18.1
Requires-Dist: toolz ==0.12.1
Requires-Dist: typing-extensions ==4.12.2
Requires-Dist: urllib3 ==2.2.2
Requires-Dist: web3 ==6.19.0
Requires-Dist: websockets ==12.0
Requires-Dist: yarl ==1.9.4
